{"offices": [{"name": "TX State Senator", "divisionId": "ocd-division/country:us/state:tx/sldu:2", "levels": ["administrativeArea1"], "roles": ["legislatorUpperBody"], "officialIndices": [0]}], "officials": [{"name": "Bob Hall", "address": [{"line1": "P.O. Box 12068", "line2": "Capitol Station", "line3": "", "city": "Austin", "state": "TX", "zip": "78711"}, {"line1": "17585 State Highway 19", "line2": "Suite 200", "line3": "", "city": "Canton", "state": "TX", "zip": "75103"}], "party": "Republican Party", "phones": ["(972) 722-3131"], "urls": ["https://senate.texas.gov/member.php?d=2"], "photoUrl": "http://www.senate.texas.gov/members/d02/img/headshot.jpg", "emails": ["bob.hall@senate.texas.gov"], "channels": [{"type": "Facebook", "id": "SenatorBobHall"}, {"type": "Twitter", "id": "SenatorBobHall"}]}], "divisions": {"ocd-division/country:us/state:tx/sldu:2": {"name": "Texas State Senate district 2", "officeIndices": [0]}}}