{"offices": [{"name": "TX State Representative", "divisionId": "ocd-division/country:us/state:tx/sldl:135", "levels": ["administrativeArea1"], "roles": ["legislatorLowerBody"], "officialIndices": [0]}], "officials": [{"name": "Jon E. Rosenthal", "party": "Democratic Party", "phones": ["(512) 463-0722"], "urls": ["https://house.texas.gov/members/member-page/?district=135"], "emails": ["jon.rosenthal@house.texas.gov"], "channels": [{"type": "Facebook", "id": "JonRosenthalTX"}]}], "divisions": {"ocd-division/country:us/state:tx/sldl:135": {"name": "Texas State House district 135", "officeIndices": [0]}}}